sampleworld.py
sampleworld_rb-0.0.1.dist-info/LICENSE.txt
sampleworld_rb-0.0.1.dist-info/METADATA
sampleworld_rb-0.0.1.dist-info/WHEEL
sampleworld_rb-0.0.1.dist-info/top_level.txt
sampleworld_rb-0.0.1.dist-info/RECORD
