Metadata-Version: 2.1
Name: sampleworld-rb
Version: 0.0.1
Summary: Just a sample package for python package development
Home-page: https://github.com/rizwanbutt314/python-package-development
Author: Rizwan Hameed
Author-email: rizwanbutt314@gmail.com
License: UNKNOWN
Platform: UNKNOWN
Classifier: Programming Language :: Python :: 3
Classifier: Programming Language :: Python :: 3.6
Classifier: Programming Language :: Python :: 3.7
